pyvstress/__about__.py
pyvstress/__init__.py
pyvstress/exceptions.py
pyvstress/soil.py
pyvstress/utility_functions.py
pyvstress-0.0.3.dist-info/LICENSE.md
pyvstress-0.0.3.dist-info/METADATA
pyvstress-0.0.3.dist-info/WHEEL
pyvstress-0.0.3.dist-info/RECORD
