Metadata-Version: 2.1
Name: pyvstress
Version: 0.0.3
Summary: A minimal code to compute vertical stresses in horizontal soil profile.
Home-page: https://gitlab.com/geosharma/pyvstress
License:  GPL-3.0-or-later
Keywords: Soil Mechanics,Geotechnical Engineering,Vertical Stresses,Soil Profile
Author: Aashish Sharma
Author-email: confusionaananda@gmail.com
Requires-Python: >=3.11,<4.0
Classifier: Development Status :: 1 - Planning
Classifier: License :: OSI Approved :: GNU General Public License v3 (GPLv3)
Classifier: License :: Other/Proprietary License
Classifier: Operating System :: OS Independent
Classifier: Programming Language :: Python :: 3
Classifier: Programming Language :: Python :: 3.11
Requires-Dist: numpy (>=1.25.2,<2.0.0)
Project-URL: Documentation, https://pyvstress.readthedocs.io/index.html
Project-URL: Repository, https://gitlab.com/geosharma/pyvstress
